imBroker/__init__.py
imBroker/broker.py
imBroker-0.0.1.dist-info/LICENSE
imBroker-0.0.1.dist-info/METADATA
imBroker-0.0.1.dist-info/WHEEL
imBroker-0.0.1.dist-info/top_level.txt
imBroker-0.0.1.dist-info/RECORD
