Metadata-Version: 2.1
Name: imBroker
Version: 0.0.1
Summary: A Tensorflow Lite Image Classification Model Integration Library
Author: dakshoza (Daksh Oza)
Author-email: <ozadaksh31@gmail.com>
Project-URL: Bug Tracker, https://github.com/yourusername/disPred/issues
Project-URL: Source Code, https://github.com/yourusername/disPred
Keywords: broker,tensorflow lite,image classification,flexible,real time
Classifier: Development Status :: 3 - Alpha
Classifier: Intended Audience :: Developers
Classifier: Topic :: Scientific/Engineering :: Artificial Intelligence
Classifier: Topic :: Scientific/Engineering :: Image Recognition
Classifier: Operating System :: OS Independent
Requires-Python: >=3.7
License-File: LICENSE
Requires-Dist: opencv-python (==4.8.0.74)
Requires-Dist: numpy (==1.23.5)
Requires-Dist: tensorflow (==2.14.0)
